README
setup.cfg
setup.py
lib/amaze/__init__.py
lib/amaze/image.py
lib/amaze/terminal.py
lib/maze/__init__.py
lib/maze/_info.py
lib/maze/halls.py
lib/maze/hex.py
lib/maze/quad.py
lib/maze/randomized_prim.py
lib/maze/tri.py
lib/pymaze.egg-info/PKG-INFO
lib/pymaze.egg-info/SOURCES.txt
lib/pymaze.egg-info/dependency_links.txt
lib/pymaze.egg-info/requires.txt
lib/pymaze.egg-info/top_level.txt
lib/pymaze.egg-info/zip-safe
tools/amaze