Metadata-Version: 1.0
Name: pymaze
Version: 1.2.3
Summary: A library to generate and display mazes
Home-page: https://github.com/moses-palmer/maze.py
Author: Moses PalmÃ©r
Author-email: moses.palmer@gmail.com
License: GPLv3
Platform: UNKNOWN
